mcoauth/__init__.py
mcoauth/mcoauth.py
mcoauth-0.0.4.dist-info/LICENSE
mcoauth-0.0.4.dist-info/METADATA
mcoauth-0.0.4.dist-info/WHEEL
mcoauth-0.0.4.dist-info/top_level.txt
mcoauth-0.0.4.dist-info/RECORD
