Metadata-Version: 2.1
Name: mcoauth
Version: 0.0.4
Summary: A small package to use MCOauth
Home-page: https://github.com/MySixSenses/MCOauth
Author: TheUltimateGuide
Author-email: theultimateguideofficial@gmail.com
License: UNKNOWN
Platform: UNKNOWN
Classifier: Programming Language :: Python :: 3
Classifier: License :: OSI Approved :: MIT License
Classifier: Operating System :: OS Independent
Requires-Python: >=3.6
Requires-Dist: aiohttp
